py_olx/__init__.py
py_olx/ads.py
py_olx/auth.py
py_olx/client.py
py_olx/exceptions.py
py_olx/olx.py
py_olx/user.py
py_olx_client-0.1.1.dist-info/LICENSE
py_olx_client-0.1.1.dist-info/METADATA
py_olx_client-0.1.1.dist-info/WHEEL
py_olx_client-0.1.1.dist-info/top_level.txt
py_olx_client-0.1.1.dist-info/RECORD
