Metadata-Version: 2.1
Name: py-olx-client
Version: 0.1.1
Summary: Python client for interacting with the OLX API
Home-page: https://github.com/Bogdangarantov/py-olx
Author: its_bohdan
Author-email: harysh.bogdan@gmail.com
Project-URL: GitHub, https://github.com/Bogdangarantov/py-olx
Keywords: olx api olxapi
Classifier: Programming Language :: Python :: 3.11
Classifier: License :: OSI Approved :: MIT License
Classifier: Operating System :: OS Independent
Requires-Python: >=3.11
License-File: LICENSE
Requires-Dist: requests >=2.32.3
Requires-Dist: setuptools >=68.2.0
